{
  "version": 1,
  "action": "death",
  "direction": "w",
  "mode": "image",
  "spritesheet": "death.png",
  "previewGif": "death.gif",
  "frameWidth": 256,
  "frameHeight": 256,
  "columns": 5,
  "rows": 1,
  "frames": 5,
  "fps": 8,
  "anchor": {
    "x": 128,
    "y": 255
  },
  "sourceRun": "runs/robin-chute-v3-death-from-resnap-02-k16-retry-01/generated/sheet.png",
  "pixelSnap": false,
  "sourceDetail": "image pose-board retry rebuild without pixel snap, curated frames 2,5,6,7,8",
  "curatedFrameOrder": [
    2,
    5,
    6,
    7,
    8
  ],
  "runtimeFinalization": {
    "anchorPolicy": "grounded",
    "requestedAnchorPolicy": "auto",
    "targetBottomY": 255,
    "targetCenterX": 128,
    "framesAdjusted": 0,
    "report": "finalize-runtime.json"
  },
  "sourceManifest": "runs/20260514-080929-robin-chute-v3-nosnap-spritesheets/animations/death/manifest.json"
}
